HISTORY.txt
README.txt
setup.py
plone/__init__.py
plone.recipe.runscript.egg-info/PKG-INFO
plone.recipe.runscript.egg-info/SOURCES.txt
plone.recipe.runscript.egg-info/dependency_links.txt
plone.recipe.runscript.egg-info/entry_points.txt
plone.recipe.runscript.egg-info/namespace_packages.txt
plone.recipe.runscript.egg-info/not-zip-safe
plone.recipe.runscript.egg-info/requires.txt
plone.recipe.runscript.egg-info/top_level.txt
plone/recipe/__init__.py
plone/recipe/runscript/__init__.py
