Metadata-Version: 1.0
Name: plone.recipe.runscript
Version: 0.3.1
Summary: A buildout recipe to run a zope script
Home-page: https://svn.plone.org/svn/collective/buildout/plone.recipe.runscript/tags/0.3.1
Author: Stefan Eletzhofer
Author-email: stefan.eletzhofer@inquant.de
License: GPL
Keywords: framework buildout recipe zope
Platform: UNKNOWN
Classifier: Framework :: Buildout
Classifier: Framework :: Zope2
Classifier: Framework :: Zope3
Classifier: Programming Language :: Python
Classifier: Topic :: Software Development :: Libraries :: Python Modules
